{"var_num":43,"label":"Neonatal mortality rate","measure":"Percent","countries":{"AGO":{"country":"Angola","code":"AGO","data":[{"year":2011,"source":"MIS","value":23}]},"BDI":{"country":"Burundi","code":"BDI","data":[{"year":1987,"source":"DHS","value":35},{"year":2010,"source":"DHS","value":31}]},"BFA":{"country":"Burkina Faso","code":"BFA","data":[{"year":1993,"source":"DHS","value":43},{"year":1999,"source":"DHS","value":41},{"year":2003,"source":"DHS","value":31},{"year":2010,"source":"DHS","value":28}]},"BGD":{"country":"Bangladesh","code":"BGD","data":[{"year":1994,"source":"DHS","value":52},{"year":1997,"source":"DHS","value":48},{"year":2000,"source":"DHS","value":42},{"year":2004,"source":"DHS","value":41},{"year":2007,"source":"DHS","value":37},{"year":2011,"source":"IPUMS","value":32}]},"CIV":{"country":"Cote d'Ivoire","code":"CIV","data":[{"year":1994,"source":"DHS","value":42},{"year":1998,"source":"DHS","value":62},{"year":2005,"source":"AIS","value":41},{"year":2012,"source":"DHS","value":38}]},"CMR":{"country":"Cameroon","code":"CMR","data":[{"year":1991,"source":"DHS","value":33},{"year":1998,"source":"DHS","value":37},{"year":2004,"source":"DHS","value":29},{"year":2011,"source":"DHS","value":31}]},"EGY":{"country":"Egypt","code":"EGY","data":[{"year":1988,"source":"DHS","value":38},{"year":1992,"source":"DHS","value":33},{"year":1995,"source":"DHS","value":30},{"year":2000,"source":"DHS","value":24},{"year":2003,"source":"DHS","value":23},{"year":2005,"source":"DHS","value":20},{"year":2008,"source":"DHS","value":16},{"year":2014,"source":"DHS","value":14}]},"ETH":{"country":"Ethiopia","code":"ETH","data":[{"year":2000,"source":"DHS","value":49},{"year":2005,"source":"DHS","value":39},{"year":2011,"source":"DHS","value":37}]},"GHA":{"country":"Ghana","code":"GHA","data":[{"year":1988,"source":"DHS","value":43},{"year":1993,"source":"DHS","value":41},{"year":1998,"source":"DHS","value":30},{"year":2003,"source":"DHS","value":43},{"year":2008,"source":"DHS","value":30}]},"GTM":{"country":"Guatemala","code":"GTM","data":[{"year":1987,"source":"DHS","value":33},{"year":1995,"source":"DHS","value":26},{"year":1999,"source":"DHS","value":23}]},"IDN":{"country":"Indonesia","code":"IDN","data":[{"year":1987,"source":"DHS","value":27},{"year":1991,"source":"DHS","value":32},{"year":1994,"source":"DHS","value":30},{"year":1997,"source":"DHS","value":22},{"year":2003,"source":"DHS","value":20},{"year":2007,"source":"DHS","value":19},{"year":2012,"source":"DHS","value":19}]},"IND":{"country":"India","code":"IND","data":[{"year":1993,"source":"IPUMS","value":49},{"year":1999,"source":"IPUMS","value":43},{"year":2006,"source":"DHS","value":39}]},"KEN":{"country":"Kenya","code":"KEN","data":[{"year":1989,"source":"BOTH","value":28},{"year":1993,"source":"DHS","value":26},{"year":1998,"source":"DHS","value":28},{"year":2003,"source":"DHS","value":33},{"year":2008,"source":"DHS","value":31}]},"KHM":{"country":"Cambodia","code":"KHM","data":[{"year":2000,"source":"DHS","value":37},{"year":2005,"source":"DHS","value":28},{"year":2010,"source":"DHS","value":27},{"year":2014,"source":"DHS","value":18}]},"MDG":{"country":"Madagascar","code":"MDG","data":[{"year":1992,"source":"DHS","value":39},{"year":1997,"source":"DHS","value":40},{"year":2004,"source":"DHS","value":32},{"year":2008,"source":"DHS","value":24}]},"MLI":{"country":"Mali","code":"MLI","data":[{"year":1987,"source":"BOTH","value":51},{"year":1996,"source":"DHS","value":60},{"year":2001,"source":"DHS","value":57},{"year":2006,"source":"DHS","value":46},{"year":2012,"source":"DHS","value":34}]},"MOZ":{"country":"Mozambique","code":"MOZ","data":[{"year":1997,"source":"BOTH","value":54},{"year":2003,"source":"DHS","value":37},{"year":2011,"source":"DHS","value":30}]},"MWI":{"country":"Malawi","code":"MWI","data":[{"year":1992,"source":"DHS","value":41},{"year":2000,"source":"DHS","value":42},{"year":2004,"source":"DHS","value":27},{"year":2010,"source":"DHS","value":31}]},"NER":{"country":"Niger","code":"NER","data":[{"year":1992,"source":"DHS","value":41},{"year":1998,"source":"DHS","value":44},{"year":2006,"source":"DHS","value":33},{"year":2012,"source":"DHS","value":24}]},"NGA":{"country":"Nigeria","code":"NGA","data":[{"year":1990,"source":"DHS","value":42},{"year":1999,"source":"DHS","value":37},{"year":2003,"source":"DHS","value":48},{"year":2008,"source":"BOTH","value":40},{"year":2010,"source":"BOTH","value":42},{"year":2013,"source":"DHS","value":37}]},"PAK":{"country":"Pakistan","code":"PAK","data":[{"year":1991,"source":"DHS","value":49},{"year":2006,"source":"DHS","value":54},{"year":2012,"source":"DHS","value":55}]},"PER":{"country":"Peru","code":"PER","data":[{"year":1986,"source":"DHS","value":35},{"year":1992,"source":"DHS","value":25},{"year":1996,"source":"DHS","value":24},{"year":2000,"source":"DHS","value":18},{"year":2004,"source":"DHS","value":13},{"year":2007,"source":"IPUMS","value":10},{"year":2009,"source":"DHS","value":11},{"year":2010,"source":"DHS","value":9},{"year":2011,"source":"DHS","value":8},{"year":2012,"source":"DHS","value":10}]},"PHL":{"country":"Philippines","code":"PHL","data":[{"year":1993,"source":"DHS","value":18},{"year":1998,"source":"DHS","value":18},{"year":2003,"source":"DHS","value":17},{"year":2008,"source":"DHS","value":16},{"year":2013,"source":"DHS","value":13}]},"RWA":{"country":"Rwanda","code":"RWA","data":[{"year":1992,"source":"DHS","value":39},{"year":2000,"source":"DHS","value":44},{"year":2005,"source":"DHS","value":37},{"year":2008,"source":"DHS","value":28},{"year":2010,"source":"DHS","value":27}]},"SDN":{"country":"Sudan","code":"SDN","data":[{"year":1990,"source":"DHS","value":44}]},"TCD":{"country":"Chad","code":"TCD","data":[{"year":1997,"source":"DHS","value":44},{"year":2004,"source":"DHS","value":39}]},"TUR":{"country":"Turkey","code":"TUR","data":[{"year":1993,"source":"DHS","value":29},{"year":1998,"source":"DHS","value":26}]},"TZA":{"country":"Tanzania","code":"TZA","data":[{"year":1992,"source":"DHS","value":38},{"year":1996,"source":"DHS","value":32},{"year":1999,"source":"DHS","value":40},{"year":2005,"source":"DHS","value":32},{"year":2007,"source":"AIS","value":29},{"year":2010,"source":"DHS","value":26}]},"UGA":{"country":"Uganda","code":"UGA","data":[{"year":1988,"source":"DHS","value":43},{"year":1995,"source":"DHS","value":27},{"year":2000,"source":"DHS","value":33},{"year":2006,"source":"DHS","value":27},{"year":2009,"source":"DHS","value":28},{"year":2011,"source":"DHS","value":27}]},"VNM":{"country":"Vietnam","code":"VNM","data":[{"year":1997,"source":"DHS","value":18},{"year":2002,"source":"DHS","value":12}]},"YEM":{"country":"Yemen","code":"YEM","data":[{"year":1991,"source":"DHS","value":41},{"year":1997,"source":"DHS","value":34},{"year":2013,"source":"DHS","value":26}]},"ZAF":{"country":"South Africa","code":"ZAF","data":[{"year":1998,"source":"DHS","value":20}]},"ZMB":{"country":"Zambia","code":"ZMB","data":[{"year":1992,"source":"DHS","value":43},{"year":1996,"source":"DHS","value":35},{"year":2002,"source":"DHS","value":37},{"year":2007,"source":"DHS","value":34},{"year":2013,"source":"DHS","value":24}]}}}